prime_nums/__init__.py
prime_nums-3.0.0.dist-info/LICENSE
prime_nums-3.0.0.dist-info/METADATA
prime_nums-3.0.0.dist-info/WHEEL
prime_nums-3.0.0.dist-info/top_level.txt
prime_nums-3.0.0.dist-info/RECORD
