Metadata-Version: 2.1
Name: prime-nums
Version: 3.0.0
Summary: prime numbers generator and checker
Home-page: https://github.com/SilasPDJ/pypi_project_nums_primos
Author: silaspdj
Author-email: silsilinhas@gmail.com
Project-URL: Bug Tracker, https://github.com/SilasPDJ/pypi_project_nums_primos/issues
Classifier: Programming Language :: Python :: 3
Classifier: License :: OSI Approved :: MIT License
Classifier: Operating System :: OS Independent
Requires-Python: >=3.6
License-File: LICENSE
